[{"id":"c6962f1d-f756-4b8e-8efe-8ba1d5301384","slug":"damian-soo","name":"Damian Soto","avatar":"https://pbs.twimg.com/profile_images/1333786961929150464/QDm4Y32L_normal.png","links":[{"url":"https://twitter.com/sotoplatero","title":"dsoto (@sotoplatero) / Twitter","publisher":"Twitter","logo":"https://logo.clearbit.com/twitter.com","avatar":"https://pbs.twimg.com/profile_images/1333786961929150464/QDm4Y32L_normal.png"},{"url":"https://github.com/sotoplatero","title":"sotoplatero - Overview","publisher":"GitHub","logo":"https://logo.clearbit.com/github.com","avatar":"https://avatars.githubusercontent.com/u/1093661?s=400&v=4"},{"url":"https://dsoto.dev","title":"dsoto","publisher":"dsoto.dev","logo":"https://dsoto.dev/favicon.jpg"}]},{"id":"93901e48-bde3-414c-bcf1-f26244e5d7ca","slug":"soto-test","name":"Damian Soto","avatar":"https://pbs.twimg.com/profile_images/1333786961929150464/QDm4Y32L_normal.png","links":[]},{"id":"1166c66c-2cbe-4450-bdd2-3816c00c1867","slug":"dsoto","name":"dsoto","avatar":"https://pbs.twimg.com/profile_images/1333786961929150464/QDm4Y32L_normal.png","links":[{"url":"https://twitter.com/sotoplatero","title":"dsoto (@sotoplatero) / Twitter","publisher":"Twitter","logo":"https://logo.clearbit.com/twitter.com","avatar":"https://pbs.twimg.com/profile_images/1333786961929150464/QDm4Y32L_normal.png"},{"url":"https://github.com/sotoplatero","title":"sotoplatero - Overview","publisher":"GitHub","logo":"https://logo.clearbit.com/github.com","avatar":"https://avatars.githubusercontent.com/u/1093661?s=400&v=4"},{"url":"https://dsoto.dev","title":"dsoto","publisher":"dsoto.dev","logo":"https://dsoto.dev/favicon.jpg"}]},{"id":"15c04829-7464-4c4a-b61e-82883cc92a3d","slug":"damian","name":"Damian","avatar":"https://pbs.twimg.com/profile_images/1333786961929150464/QDm4Y32L_normal.png","links":[{"url":"https://twitter.com/sotoplatero","title":"dsoto (@sotoplatero) / Twitter","publisher":"Twitter","logo":"https://logo.clearbit.com/twitter.com","avatar":"https://pbs.twimg.com/profile_images/1333786961929150464/QDm4Y32L_normal.png"}]},{"id":"ceb71d44-6d2c-441c-9696-8f5658cfc507","slug":"dsoto","name":"dsoto","avatar":"https://pbs.twimg.com/profile_images/1333786961929150464/QDm4Y32L_normal.png","links":[{"url":"https://twitter.com/sotoplatero","title":"dsoto (@sotoplatero) / Twitter","publisher":"Twitter","logo":"https://logo.clearbit.com/twitter.com","avatar":"https://pbs.twimg.com/profile_images/1333786961929150464/QDm4Y32L_normal.png"},{"url":"https://github.com/sotoplatero","title":"sotoplatero - Overview","publisher":"GitHub","logo":"https://logo.clearbit.com/github.com","avatar":"https://avatars.githubusercontent.com/u/1093661?s=400&v=4"},{"url":"https://dsoto.dev","title":"dsoto","publisher":"dsoto.dev","logo":"https://dsoto.dev/favicon.jpg"}]},{"id":"102e721c-89b3-4778-9e98-4eee172354fe","slug":"website","name":"Website","avatar":"https://images.unsplash.com/photo-1487088678257-3a541e6e3922?ixid=MXwxMjA3fDB8MHxwaG90by1wYWdlfHx8fGVufDB8fHw%3D&ixlib=rb-1.2.1&auto=format&fit=crop&w=667&q=80","links":[{"url":"https://iamraul.net","title":"Mi nombre es Raúl | @imraul","publisher":"iamraul.net","logo":"https://iamraul.net/favicon.svg","avatar":"https://images.unsplash.com/photo-1487088678257-3a541e6e3922?ixid=MXwxMjA3fDB8MHxwaG90by1wYWdlfHx8fGVufDB8fHw%3D&ixlib=rb-1.2.1&auto=format&fit=crop&w=667&q=80"}]},{"id":"e8907842-d079-4a0f-a365-e73d57d3304a","slug":"test","name":"Test","avatar":"https://pbs.twimg.com/profile_images/1283591826042167297/ofXTvx4q_normal.jpg","links":[{"url":"https://twitter.com/pedris11s","title":"Pedro Torres (@pedris11s) / Twitter","publisher":"Twitter","logo":"https://logo.clearbit.com/twitter.com","avatar":"https://pbs.twimg.com/profile_images/1283591826042167297/ofXTvx4q_normal.jpg"},{"url":"https://github.com/pedris11s","title":"pedris11s - Overview","publisher":"GitHub","logo":"https://logo.clearbit.com/github.com","avatar":"https://avatars.githubusercontent.com/u/48369986?s=400&u=9ae705a807350096a9d9c25489b534878b23b24e&v=4"}]},{"id":"2e8bd895-af30-4d94-a1bd-8e1cd590aea7","slug":"carlos-lugones","name":"Carlos Lugones","avatar":"https://pbs.twimg.com/profile_images/1350271505637269506/v0Efd1Aq_normal.jpg","links":[{"url":"https://twitter.com/lugodev","title":"Carlos Lugones (@lugodev) / Twitter","publisher":"Twitter","logo":"https://logo.clearbit.com/twitter.com","avatar":"https://pbs.twimg.com/profile_images/1350271505637269506/v0Efd1Aq_normal.jpg"},{"url":"https://vero.co/lugodev","title":"Carlos Lugones on VERO™","publisher":"Carlos Lugones on VERO™","logo":"https://logo.clearbit.com/vero.co","avatar":"https://d1dpu3msttfsqg.cloudfront.net/a069d160-63d7-11eb-9148-a79edc32b315/087d8373-e1e1-4162-8ca8-09b1f39b2eb0"},{"url":"https://www.youtube.com/channel/UCS-cWLGwGoijpnmBrzFgJzA","title":"Carlos Lugones","publisher":"YouTube","logo":"https://logo.clearbit.com/youtube.com","avatar":"https://yt3.ggpht.com/ytc/AAUvwnjInkb3JsbialRKSP54tZY3caYnAQ40OgdSmg9x=s900-c-k-c0x00ffffff-no-rj"},{"url":"https://lugodev.medium.com","title":"Carlos Lugones – Medium","publisher":"Medium","logo":"https://logo.clearbit.com/medium.com","avatar":"https://miro.medium.com/max/2400/1*EoesLrzOVvIWayrDNno80Q.jpeg"},{"url":"https://linkedin.com/in/lugodev","title":"lugodev","publisher":"linkedin.com","logo":"https://logo.clearbit.com/linkedin.com"},{"url":"https://www.facebook.com/login/?next=https%3A%2F%2Fwww.facebook.com%2Flugodev","title":"Log into Facebook","publisher":"Facebook","logo":"https://logo.clearbit.com/facebook.com","avatar":"https://static.xx.fbcdn.net/rsrc.php/y8/r/dF5SId3UHWd.svg"},{"url":"https://angel.co/u/lugodev","title":"angel.co","publisher":"angel.co","logo":"https://logo.clearbit.com/angel.co"},{"url":"https://github.com/lugodev","title":"lugodev - Overview","publisher":"GitHub","logo":"https://logo.clearbit.com/github.com","avatar":"https://avatars.githubusercontent.com/u/18733370?s=400&u=e147ed17f0b4d7574dc62c8138131f614cd6bb05&v=4"}]}]